lsmcmc/__init__.py
lsmcmc/algorithms.py
lsmcmc/logging.py
lsmcmc/model.py
lsmcmc/output.py
lsmcmc/py.typed
lsmcmc/sampling.py
lsmcmc/storage.py
lsmcmc-0.0.0.dist-info/licenses/LICENSE
lsmcmc-0.0.0.dist-info/METADATA
lsmcmc-0.0.0.dist-info/WHEEL
lsmcmc-0.0.0.dist-info/top_level.txt
lsmcmc-0.0.0.dist-info/RECORD
